OdooLocust/OdooLocustUser.py
OdooLocust/OdooTaskSet.py
OdooLocust/__init__.py
OdooLocust/crm/__init__.py
OdooLocust/crm/lead.py
OdooLocust/crm/partner.py
OdooLocust/crm/quotation.py
odoolocust-1.6.9.dist-info/METADATA
odoolocust-1.6.9.dist-info/WHEEL
odoolocust-1.6.9.dist-info/top_level.txt
odoolocust-1.6.9.dist-info/RECORD
