Metadata-Version: 2.4
Name: OdooLocust
Version: 1.6.9
Summary: Easily load test Odoo using Locust and odoolib.
Home-page: 
Author: Nicolas Seinlet
Author-email: 
License: BSD
Keywords: odoo locust odoolib loadtest
Classifier: License :: OSI Approved :: BSD License
Classifier: Programming Language :: Python
Requires-Dist: odoo-client-lib>=1.2.2
Requires-Dist: locust>=2.35.0
Requires-Dist: names>=0.3.0
Dynamic: author
Dynamic: classifier
Dynamic: description
Dynamic: keywords
Dynamic: license
Dynamic: requires-dist
Dynamic: summary
